part_library_gen/__init__.py
part_library_gen/app.py
part_library_gen/symbol_generator.py
part_library_gen/generators/__init__.py
part_library_gen/generators/default_generator.py
part_library_gen/generators/rectangular_symbol_generator.py
part_library_gen/generators/components/__init__.py
part_library_gen/generators/components/designator.py
part_library_gen/generators/components/part_number.py
part_library_gen/generators/components/pin.py
part_library_gen/generators/components/rectangle.py
part_library_gen/generators/components/symbol.py
part_library_gen-0.1.1.dist-info/LICENSE
part_library_gen-0.1.1.dist-info/METADATA
part_library_gen-0.1.1.dist-info/WHEEL
part_library_gen-0.1.1.dist-info/entry_points.txt
part_library_gen-0.1.1.dist-info/top_level.txt
part_library_gen-0.1.1.dist-info/RECORD
