Metadata-Version: 2.1
Name: part_library_gen
Version: 0.1.1
Summary: Library that generates electronics components symbols from json data.
Home-page: https://github.com/partmanager/part-library-gen
Author: sakoPO
Project-URL: Bug Tracker, https://github.com/partmanager/part-library-gen/issues
Project-URL: Changelog, https://github.com/partmanager/part-library-gen/releases
Project-URL: Source Code, https://github.com/partmanager/part-library-gen
Project-URL: Documentation, https://partmanager.github.io/part-library-gen
Classifier: Programming Language :: Python :: 3
Classifier: Intended Audience :: Developers
Classifier: Intended Audience :: Manufacturing
Classifier: License :: OSI Approved :: GNU General Public License v3 (GPLv3)
Classifier: Operating System :: OS Independent
Requires-Python: >=3.9
License-File: LICENSE
